jutil/configuration.py
jutil/database.py
jutil/installation.py
jutil/logging.py
jutil/processing.py
jutil/database/__init__.py
jutil/database/sqlalchemy.py
jutily-0.0.0.22.dist-info/DESCRIPTION.rst
jutily-0.0.0.22.dist-info/METADATA
jutily-0.0.0.22.dist-info/RECORD
jutily-0.0.0.22.dist-info/WHEEL
jutily-0.0.0.22.dist-info/metadata.json
jutily-0.0.0.22.dist-info/top_level.txt
