Metadata-Version: 2.0
Name: jutily
Version: 0.0.0.22
Summary: UNKNOWN
Home-page: https://github.com/the16thpythonist/ScopusWp
Author: Jonas Teufel
Author-email: jonseb1998@gmail.com
License: MIT
Platform: UNKNOWN
Requires-Python: >=3, <4
Requires-Dist: deprecated
Requires-Dist: jinja2 (>=2.10)
Requires-Dist: sqlalchemy (>=1.2)
